{"stats":{"minecraft:used":{"minecraft:netherite_sword":4},"minecraft:custom":{"minecraft:jump":2,"minecraft:time_since_rest":306,"minecraft:damage_dealt":260,"minecraft:crouch_one_cm":73,"minecraft:leave_game":1,"minecraft:sprint_one_cm":203,"minecraft:play_time":306,"minecraft:time_since_death":306,"minecraft:walk_one_cm":902,"minecraft:sneak_time":23,"minecraft:total_world_time":418,"minecraft:mob_kills":1,"minecraft:fly_one_cm":5453},"minecraft:picked_up":{"minecraft:leather":2},"minecraft:killed":{"minecraft:horse":1}},"DataVersion":3700}